typez/.gitignore
typez/__init__.py
typez/package.json
typez/schema.json
typez/tmp.yaml
typez/tsconfig.json
typez/yarn.lock
typez/src/.gitignore
typez/src/CytoscapeComponent.tsx
typez/src/GraphComponent.tsx
typez/src/SelectState.tsx
typez/src/State.ts
typez/src/extension.tsx
typez/src/getSafe.ts
typez/src/index.tsx
typez/src/schema.ts
typez/src/usePrevious.tsx
typez/types/cytoscape-dagre/index.d.ts
typez/types/cytoscape-elk-saul/index.d.ts
typez/types/cytoscape-klay/index.d.ts
typez-0.4.0.dist-info/WHEEL
typez-0.4.0.dist-info/METADATA
typez-0.4.0.dist-info/RECORD
