Metadata-Version: 2.1
Name: typez
Version: 0.4.0
Summary: Meta language for describing DSLs in JSON.
Home-page: https://github.com/Quansight-Labs/metadsl
License: UNKNOWN
Author: Saul Shanabrook
Author-email: s.shanabrook@gmail.com
Classifier: Intended Audience :: Developers
Classifier: License :: OSI Approved :: BSD License
Classifier: Programming Language :: Python :: 3
Classifier: Programming Language :: Python :: 3.7
Classifier: Topic :: Software Development :: Libraries :: Python Modules
Requires-Dist: jsonschema
Requires-Dist: IPython
